LICENSE
README.md
puffb.py
setup.cfg
setup.py
puffb.egg-info/PKG-INFO
puffb.egg-info/SOURCES.txt
puffb.egg-info/dependency_links.txt
puffb.egg-info/requires.txt
puffb.egg-info/top_level.txt